{
  "width": 20,
  "height": 20,
  "agents": 30,
  "start": [
    111,
    288,
    285,
    244,
    31,
    271,
    388,
    12,
    162,
    78,
    394,
    18,
    115,
    396,
    209,
    261,
    280,
    169,
    29,
    197,
    242,
    199,
    42,
    282,
    25,
    193,
    191,
    367,
    369,
    140
  ],
  "end": [
    154,
    124,
    19,
    110,
    298,
    320,
    23,
    389,
    342,
    229,
    256,
    168,
    380,
    60,
    92,
    78,
    186,
    197,
    308,
    361,
    279,
    384,
    131,
    230,
    260,
    319,
    237,
    339,
    394,
    153
  ],
  "time": 34,
  "obstacles": []
}